llvmcpy/__init__.py
llvmcpy/_generator.py
llvmcpy/tests/__init__.py
llvmcpy/tests/concurrent.py
llvmcpy/tests/main.py
llvmcpy-0.2.1.dist-info/licenses/LICENSE.txt
llvmcpy-0.2.1.dist-info/METADATA
llvmcpy-0.2.1.dist-info/WHEEL
llvmcpy-0.2.1.dist-info/top_level.txt
llvmcpy-0.2.1.dist-info/RECORD
