Metadata-Version: 2.4
Name: llvmcpy
Version: 0.2.1
Summary: Python bindings for LLVM auto-generated from the LLVM-C API
Author-email: Alessandro Di Federico <ale.llvmcpy@clearmind.me>
License: MIT License
Project-URL: Repository, https://github.com/revng/llvmcpy
Keywords: llvm
Classifier: Development Status :: 3 - Alpha
Classifier: Intended Audience :: Developers
Classifier: License :: OSI Approved :: MIT License
Classifier: Programming Language :: Python :: 3
License-File: LICENSE.txt
Requires-Dist: cffi>=1.0.0
Requires-Dist: pycparser
Requires-Dist: platformdirs
Requires-Dist: setuptools; python_version < "3.8"
Dynamic: license-file
